imgproc/__init__.py
imgproc/cpp/Binarization.cpp
imgproc/cpp/Binarization.hpp
imgproc/cpp/LineSegmentation.cpp
imgproc/cpp/LineSegmentation.hpp
imgproc/cpp/Scanner.cpp
imgproc/cpp/Scanner.hpp
imgproc/cpp/main.cpp
textsegmt-0.1.0.dist-info/METADATA
textsegmt-0.1.0.dist-info/WHEEL
textsegmt-0.1.0.dist-info/top_level.txt
textsegmt-0.1.0.dist-info/RECORD
